.DS_Store
flet_camera/.DS_Store
flet_camera/__init__.py
flet_camera-0.0.1.dist-info/.DS_Store
flet_camera-0.0.1.dist-info/METADATA
flet_camera-0.0.1.dist-info/WHEEL
flet_camera-0.0.1.dist-info/RECORD
