Metadata-Version: 2.1
Name: flet-camera
Version: 0.0.1
Summary: Flet Camera control
Author: Appveyor Systems Inc.
Author-email: hello@flet.dev
Requires-Python: >=3.8,<4.0
Project-URL: homepage, https://flet.dev
Download-URL:
